GrammarlyAPI/__init__.py
GrammarlyAPI/app.py
GrammarlyAPI/static/script.js
GrammarlyAPI/static/style.css
GrammarlyAPI/templates/index.html
GrammarlyAPI-0.1.0.dist-info/METADATA
GrammarlyAPI-0.1.0.dist-info/WHEEL
GrammarlyAPI-0.1.0.dist-info/entry_points.txt
GrammarlyAPI-0.1.0.dist-info/top_level.txt
GrammarlyAPI-0.1.0.dist-info/RECORD
